caustic/__init__.py
caustic-1.0.0.dist-info/METADATA
caustic-1.0.0.dist-info/WHEEL
caustic-1.0.0.dist-info/top_level.txt
caustic-1.0.0.dist-info/RECORD
