Metadata-Version: 2.1
Name: caustic
Version: 1.0.0
Summary: Sorry we renamed to: caustics. Please run: pip install caustics
Home-page: https://github.com/Ciela-Institute/caustic
Author: Ciela Institute
License: MIT license
Classifier: Intended Audience :: Science/Research
Classifier: License :: OSI Approved :: GNU General Public License v3 (GPLv3)
Classifier: Programming Language :: Python :: 3
Requires-Dist: numpy
